graphspire/__init__.py
graphspire/analyzer.py
graphspire/cli.py
graphspire/visualizer.py
graphspire-0.1.3.dist-info/METADATA
graphspire-0.1.3.dist-info/WHEEL
graphspire-0.1.3.dist-info/entry_points.txt
graphspire-0.1.3.dist-info/RECORD
