Metadata-Version: 2.4
Name: graphspire
Version: 0.1.3
Summary: A tool to analyze and visualize C++ project dependencies
Author-email: Kshitij <your.email@example.com>
License-Expression: MIT
Requires-Python: >=3.8
Requires-Dist: typing-extensions>=4.0.0
